recite.py
tex_recite-0.1.1.dist-info/METADATA
tex_recite-0.1.1.dist-info/WHEEL
tex_recite-0.1.1.dist-info/entry_points.txt
tex_recite-0.1.1.dist-info/RECORD
