Metadata-Version: 2.1
Name: tex-recite
Version: 0.1.1
Summary: Migrate a LaTeX document from one bibliography to another
Author: Vadim Liventsev
Author-email: dev@vadim.me
Requires-Python: >=3.7,<4.0
Classifier: Programming Language :: Python :: 3
Classifier: Programming Language :: Python :: 3.7
Classifier: Programming Language :: Python :: 3.8
Classifier: Programming Language :: Python :: 3.9
Classifier: Programming Language :: Python :: 3.10
Classifier: Programming Language :: Python :: 3.11
Classifier: Programming Language :: Python :: 3.12
Requires-Dist: bibtexparser (>=2.0.0b8,<3.0.0)
Requires-Dist: fire (>=0.5,<0.6)
Requires-Dist: texsoup (>=0.3,<0.4)
Requires-Dist: unisim[tensorflow] (>=1.0,<2.0)
